{
  "version": "1.0.0",
  "tools": [
    {
      "name": "003_implement_rate_limiting_ai_tool",
      "description": "Tool for Implement rate limiting for AI endpoints with cost monitoring and abuse prevention. All endpoints th",
      "input_schema": {
        "type": "object",
        "properties": {},
        "required": []
      },
      "output_schema": {
        "type": "object",
        "properties": {
          "success": {
            "type": "boolean"
          },
          "result": {
            "type": "object"
          }
        },
        "required": [
          "success"
        ]
      }
    }
  ]
}